pre_commit_uv_patch.pth
pre_commit_uv/__init__.py
pre_commit_uv/py.typed
pre_commit_uv-4.2.0.dist-info/METADATA
pre_commit_uv-4.2.0.dist-info/WHEEL
pre_commit_uv-4.2.0.dist-info/licenses/LICENSE.txt
pre_commit_uv-4.2.0.dist-info/RECORD
