Metadata-Version: 2.4
Name: pre-commit-uv
Version: 4.2.0
Summary: Run pre-commit with uv
Project-URL: Bug Tracker, https://github.com/tox-dev/pre-commit-uv/issues
Project-URL: Changelog, https://github.com/tox-dev/pre-commit-uv/releases
Project-URL: Documentation, https://github.com/tox-dev/pre-commit-uv/
Project-URL: Source Code, https://github.com/tox-dev/pre-commit-uv
Author-email: Bernat Gabor <gaborjbernat@gmail.com>
License: Permission is hereby granted, free of charge, to any person obtaining a
License-File: LICENSE.txt
Keywords: format,pyproject
Classifier: License :: OSI Approved :: MIT License
Classifier: Operating System :: OS Independent
Classifier: Programming Language :: Python
Classifier: Programming Language :: Python :: 3 :: Only
Classifier: Programming Language :: Python :: 3.10
Classifier: Programming Language :: Python :: 3.11
Classifier: Programming Language :: Python :: 3.12
Classifier: Programming Language :: Python :: 3.13
Classifier: Programming Language :: Python :: 3.14
Requires-Python: >=3.10
Requires-Dist: pre-commit>=4.3
Requires-Dist: uv>=0.9.1
Provides-Extra: testing
Requires-Dist: covdefaults>=2.3; extra == 'testing'
Requires-Dist: pytest-cov>=7; extra == 'testing'
Requires-Dist: pytest-mock>=3.15.1; extra == 'testing'
Requires-Dist: pytest>=8.4.2; extra == 'testing'
